{
	"hot":[{
		"name":"1.韩都衣舍2017韩版女",
		"price":88.00,
		"num":323,
		"url":"images/hot1.jpg"
	},{
		"name":"2.韩都衣舍2016秋装韩版",
		"price":881.00,
		"num":433,
		"url":"images/hot2.jpg"
	},{
		"name":"3.韩都衣舍2016韩版女",
		"price":47.00,
		"num":343,
		"url":"images/hot3.jpg"
	},{
		"name":"4.韩都衣舍2017韩版女",
		"price":83.00,
		"num":3123,
		"url":"images/hot4.jpg"
	},{
		"name":"5.韩都衣舍2017韩版",
		"price":488.00,
		"num":393,
		"url":"images/hot1.jpg"
	},{
		"name":"6.韩都衣舍2017秋装",
		"price":38.00,
		"num":43,
		"url":"images/hot2.jpg"
	},{
		"name":"7.韩都衣舍2017韩版女装",
		"price":108.00,
		"num":3233,
		"url":"images/hot3.jpg"
	},{
		"name":"8.韩都衣舍2017韩版女装",
		"price":98.00,
		"num":3343,
		"url":"images/hot4.jpg"
	}]
}