{
	"sort":[{
		"name":"韩都衣舍2017韩版女装夏装",
		"price":88.00,
		"xiao":3232,
		"contents":23,
		"id":1231,
		"url":"http://s.handu.com/images/201707/thumb_img/1499829451819149409.jpg"
	},{
		"name":"韩都衣舍2016秋装韩版百搭",
		"price":438.00,
		"xiao":323,
		"contents":223,
		"id":1232,
		"url":"http://s.handu.com/images/201709/thumb_img/1504987885123513412.jpg"
	},{
		"name":"韩都衣舍2016秋装韩版百搭",
		"price":48.00,
		"xiao":433,
		"contents":63,
		"id":1233,
		"url":"http://s.handu.com/images/201610/thumb_img/1477858289891674986.jpg"
	},{
		"name":"韩都衣舍2016秋装韩版百搭",
		"price":38.00,
		"xiao":32,
		"contents":73,
		"id":1234,
		"url":"http://s.handu.com/images/201607/thumb_img/1468527019657514084.jpg"
	},{
		"name":"韩都衣舍2016秋装韩版百搭",
		"price":4375.00,
		"xiao":33,
		"contents":27,
		"id":1235,
		"url":"http://s.handu.com/images/201605/thumb_img/1463256647982189429.jpg"
	},{
		"name":"韩都衣舍2016秋装韩版百搭",
		"price":98.00,
		"xiao":433,
		"contents":83,
		"id":1236,
		"url":"http://s.handu.com/images/201708/thumb_img/1503432636679267622.jpg"
	},{
		"name":"韩都衣舍2016秋装韩版百搭",
		"price":538.00,
		"xiao":3123,
		"contents":343,
		"id":1237,
		"url":"http://s.handu.com/images/201603/thumb_img/1459282501117262858.jpg"
	},{
		"name":"韩都衣舍2016秋装韩版百搭",
		"price":428.00,
		"xiao":63,
		"contents":133,
		"id":1238,
		"url":"http://s.handu.com/images/201703/thumb_img/1490472629482950873.jpg"
	},{
		"name":"韩都衣舍2016秋装韩版百搭",
		"price":138.00,
		"xiao":35,
		"contents":64,
		"id":1239,
		"url":"http://s.handu.com/images/201612/thumb_img/1480709466420407678.jpg"
	},{
		"name":"韩都衣舍2016秋装韩版百搭",
		"price":24.00,
		"xiao":335,
		"contents":223,
		"id":1240,
		"url":"http://s.handu.com/images/201703/thumb_img/1056203_thumb_G_1490252555160.jpg"
	},{
		"name":"韩都衣舍2016秋装韩版百搭",
		"price":3258.00,
		"xiao":3323,
		"contents":123,
		"id":1241,
		"url":"http://s.handu.com/images/201709/thumb_img/1504296651432586671.jpg"
	},{
		"name":"韩都衣舍2016秋装韩版百搭",
		"price":538.00,
		"xiao":3123,
		"contents":27,
		"id":1242,
		"url":"http://s.handu.com/images/201707/thumb_img/1501272612540619861.jpg"
	},{
		"name":"韩都衣舍2016秋装韩版百搭",
		"price":434.00,
		"xiao":312,
		"contents":245,
		"id":1243,
		"url":"http://s.handu.com/images/201705/thumb_img/1495138402759096558.jpg"
	},{
		"name":"韩都衣舍2016秋装韩版百搭",
		"price":432.00,
		"xiao":365,
		"contents":212,
		"id":1234,
		"url":"http://s.handu.com/images/201708/thumb_img/1503432660825646787.jpg"
	},{
		"name":"韩都衣舍2016秋装韩版百搭",
		"price":4325.00,
		"xiao":34,
		"contents":43,
		"id":1245,
		"url":"http://s.handu.com/images/201703/thumb_img/1489781417259079571.jpg"
	},{
		"name":"韩都衣舍2016秋装韩版百搭",
		"price":543.00,
		"xiao":3123,
		"contents":56,
		"id":1246,
		"url":"http://s.handu.com/images/201709/thumb_img/1506715838430079469.jpg"
	},{
		"name":"韩都衣舍2016秋装韩版百搭",
		"price":79.00,
		"xiao":86,
		"contents":75,
		"id":1247,
		"url":"http://s.handu.com/images/201709/thumb_img/1506024659288448285.jpg"
	},{
		"name":"韩都衣舍2016秋装韩版百搭",
		"price":478.00,
		"xiao":34,
		"contents":765,
		"id":1248,
		"url":"http://s.handu.com/images/201703/thumb_img/1489695045135412556.jpg"
	},{
		"name":"韩都衣舍2016秋装韩版百搭",
		"price":565.00,
		"xiao":345,
		"contents":786,
		"id":1249,
		"url":"http://s.handu.com/images/201708/thumb_img/1502568628263654127.jpg"
	},{
		"name":"韩都衣舍2016秋装韩版百搭",
		"price":467.00,
		"xiao":472,
		"contents":83,
		"id":1250,
		"url":"http://s.handu.com/images/201709/thumb_img/1504383010349786942.jpg"
	},{
		"name":"韩都衣舍2016秋装韩版百搭",
		"price":34.00,
		"xiao":54,
		"contents":62,
		"id":1251,
		"url":"http://s.handu.com/images/201709/thumb_img/1504296632127681400.jpg"
	},{
		"name":"韩都衣舍2016秋装韩版百搭",
		"price":466.00,
		"xiao":573,
		"contents":452,
		"id":1252,
		"url":"http://s.handu.com/images/201704/thumb_img/1493323811451973072.jpg"
	},{
		"name":"韩都衣舍2016秋装韩版百搭",
		"price":342.00,
		"xiao":15,
		"contents":54,
		"id":1253,
		"url":"http://s.handu.com/images/201703/thumb_img/1488312649709027465.jpg"
	},{
		"name":"韩都衣舍2016秋装韩版百搭",
		"price":654.00,
		"xiao":74,
		"contents":51,
		"id":1254,
		"url":"http://s.handu.com/images/201708/thumb_img/1503432633419544649.jpg"
	},{
		"name":"韩都衣舍2016秋装韩版百搭",
		"price":634.00,
		"xiao":654,
		"contents":62,
		"id":1255,
		"url":"http://s.handu.com/images/201707/thumb_img/1501272663150993279.jpg"
	},{
		"name":"韩都衣舍2016秋装韩版百搭",
		"price":35.00,
		"xiao":25,
		"contents":753,
		"id":1256,
		"url":"http://s.handu.com/images/201605/thumb_img/1463343062523682099.jpg"
	},{
		"name":"韩都衣舍2016秋装韩版百搭",
		"price":35.00,
		"xiao":64,
		"contents":73,
		"id":1257,
		"url":"http://s.handu.com/images/201704/thumb_img/1490991015662929093.jpg"
	},{
		"name":"韩都衣舍2016秋装韩版百搭",
		"price":633.00,
		"xiao":26,
		"contents":64,
		"id":1258,
		"url":"http://s.handu.com/images/201608/thumb_img/1470773466136458946.jpg"
	},{
		"name":"韩都衣舍2016秋装韩版百搭",
		"price":25.00,
		"xiao":3643,
		"contents":75,
		"id":1259,
		"url":"http://s.handu.com/images/201608/thumb_img/1471551063625516912.jpg"
	},{
		"name":"韩都衣舍2016秋装韩版百搭",
		"price":57.00,
		"xiao":73,
		"contents":95,
		"id":1260,
		"url":"http://s.handu.com/images/201704/thumb_img/1493323818699400872.jpg"
	},{
		"name":"韩都衣舍2016秋装韩版百搭",
		"price":537.00,
		"xiao":64,
		"contents":86,
		"id":1261,
		"url":"http://s.handu.com/images/201709/thumb_img/1506715840076015143.jpg"
	},{
		"name":"韩都衣舍2016秋装韩版百搭",
		"price":753.00,
		"xiao":84,
		"contents":632,
		"id":1262,
		"url":"http://s.handu.com/images/201605/thumb_img/1463256640144256437.jpg"
	},{
		"name":"韩都衣舍2016秋装韩版百搭",
		"price":634.00,
		"xiao":786,
		"contents":46,
		"id":1263,
		"url":"http://s.handu.com/images/201707/thumb_img/1501272704936123358.jpg"
	},{
		"name":"韩都衣舍2016秋装韩版百搭",
		"price":754.00,
		"xiao":87,
		"contents":85,
		"id":1264,
		"url":"http://s.handu.com/images/201704/thumb_img/1491855095200850057.jpg"
	},{
		"name":"韩都衣舍2016秋装韩版百搭",
		"price":756.00,
		"xiao":81,
		"contents":70,
		"id":1265,
		"url":"http://s.handu.com/images/201709/thumb_img/1504728715928758501.jpg"
	},{
		"name":"韩都衣舍2016秋装韩版百搭",
		"price":805.00,
		"xiao":70,
		"contents":3,
		"id":1266,		
		"url":"http://s.handu.com/images/201609/thumb_img/1046131_thumb_G_1473843851049.jpg"
	},{
		"name":"韩都衣舍2016秋装韩版百搭",
		"price":675.00,
		"xiao":746,
		"contents":678,
		"id":1267,
		"url":"http://s.handu.com/images/201708/thumb_img/1502395837350264937.jpg"
	},{
		"name":"韩都衣舍2016秋装韩版百搭",
		"price":86.00,
		"xiao":743,
		"contents":295,
		"id":1268,
		"url":"http://s.handu.com/images/201709/thumb_img/1506715838430079469.jpg"
	},{
		"name":"韩都衣舍2016秋装韩版百搭",
		"price":754.00,
		"xiao":35,
		"contents":63,
		"id":1269,
		"url":"http://s.handu.com/images/201707/thumb_img/1499199060080994589.jpg"
	},{
		"name":"韩都衣舍2016秋装韩版百搭",
		"price":531.00,
		"xiao":62,
		"contents":26,
		"id":1270,
		"url":"http://s.handu.com/images/201707/thumb_img/1500862591671331961.jpg"
	},{
		"name":"韩都衣舍2016秋装韩版百搭",
		"price":531.00,
		"xiao":62,
		"contents":26,
		"id":1270,
		"url":"http://s.handu.com/images/201707/thumb_img/1500862591671331961.jpg"
	},{
		"name":"韩都衣舍2016秋装韩版百搭",
		"price":57.00,
		"xiao":73,
		"contents":95,
		"id":1260,
		"url":"http://s.handu.com/images/201704/thumb_img/1493323818699400872.jpg"
	},{
		"name":"韩都衣舍2016秋装韩版百搭",
		"price":537.00,
		"xiao":64,
		"contents":86,
		"id":1261,
		"url":"http://s.handu.com/images/201709/thumb_img/1506715840076015143.jpg"
	},{
		"name":"韩都衣舍2016秋装韩版百搭",
		"price":753.00,
		"xiao":84,
		"contents":632,
		"id":1262,
		"url":"http://s.handu.com/images/201605/thumb_img/1463256640144256437.jpg"
	},{
		"name":"韩都衣舍2016秋装韩版百搭",
		"price":634.00,
		"xiao":786,
		"contents":46,
		"id":1263,
		"url":"http://s.handu.com/images/201707/thumb_img/1501272704936123358.jpg"
	},{
		"name":"韩都衣舍2016秋装韩版百搭",
		"price":754.00,
		"xiao":87,
		"contents":85,
		"id":1264,
		"url":"http://s.handu.com/images/201704/thumb_img/1491855095200850057.jpg"
	},{
		"name":"韩都衣舍2016秋装韩版百搭",
		"price":756.00,
		"xiao":81,
		"contents":70,
		"id":1265,
		"url":"http://s.handu.com/images/201709/thumb_img/1504728715928758501.jpg"
	},{
		"name":"韩都衣舍2016秋装韩版百搭",
		"price":805.00,
		"xiao":70,
		"contents":3,
		"id":1266,		
		"url":"http://s.handu.com/images/201609/thumb_img/1046131_thumb_G_1473843851049.jpg"
	},{
		"name":"韩都衣舍2016秋装韩版百搭",
		"price":675.00,
		"xiao":746,
		"contents":678,
		"id":1267,
		"url":"http://s.handu.com/images/201708/thumb_img/1502395837350264937.jpg"
	},{
		"name":"韩都衣舍2016秋装韩版百搭",
		"price":86.00,
		"xiao":743,
		"contents":295,
		"id":1268,
		"url":"http://s.handu.com/images/201709/thumb_img/1506715838430079469.jpg"
	},{
		"name":"韩都衣舍2016秋装韩版百搭",
		"price":754.00,
		"xiao":35,
		"contents":63,
		"id":1269,
		"url":"http://s.handu.com/images/201707/thumb_img/1499199060080994589.jpg"
	},{
		"name":"韩都衣舍2016秋装韩版百搭",
		"price":531.00,
		"xiao":62,
		"contents":26,
		"id":1270,
		"url":"http://s.handu.com/images/201707/thumb_img/1500862591671331961.jpg"
	},{
		"name":"韩都衣舍2016秋装韩版百搭",
		"price":531.00,
		"xiao":62,
		"contents":26,
		"id":1270,
		"url":"http://s.handu.com/images/201707/thumb_img/1500862591671331961.jpg"
	},{
		"name":"韩都衣舍2016秋装韩版百搭",
		"price":805.00,
		"xiao":70,
		"contents":3,
		"id":1266,		
		"url":"http://s.handu.com/images/201609/thumb_img/1046131_thumb_G_1473843851049.jpg"
	},{
		"name":"韩都衣舍2016秋装韩版百搭",
		"price":675.00,
		"xiao":746,
		"contents":678,
		"id":1267,
		"url":"http://s.handu.com/images/201708/thumb_img/1502395837350264937.jpg"
	},{
		"name":"韩都衣舍2016秋装韩版百搭",
		"price":86.00,
		"xiao":743,
		"contents":295,
		"id":1268,
		"url":"http://s.handu.com/images/201709/thumb_img/1506715838430079469.jpg"
	},{
		"name":"韩都衣舍2016秋装韩版百搭",
		"price":754.00,
		"xiao":35,
		"contents":63,
		"id":1269,
		"url":"http://s.handu.com/images/201707/thumb_img/1499199060080994589.jpg"
	},{
		"name":"韩都衣舍2016秋装韩版百搭",
		"price":531.00,
		"xiao":62,
		"contents":26,
		"id":1270,
		"url":"http://s.handu.com/images/201707/thumb_img/1500862591671331961.jpg"
	},{
		"name":"韩都衣舍2016秋装韩版百搭",
		"price":531.00,
		"xiao":62,
		"contents":26,
		"id":1270,
		"url":"http://s.handu.com/images/201707/thumb_img/1500862591671331961.jpg"
	},{
		"name":"韩都衣舍2016秋装韩版百搭",
		"price":57.00,
		"xiao":73,
		"contents":95,
		"id":1260,
		"url":"http://s.handu.com/images/201704/thumb_img/1493323818699400872.jpg"
	},{
		"name":"韩都衣舍2016秋装韩版百搭",
		"price":537.00,
		"xiao":64,
		"contents":86,
		"id":1261,
		"url":"http://s.handu.com/images/201709/thumb_img/1506715840076015143.jpg"
	},{
		"name":"韩都衣舍2016秋装韩版百搭",
		"price":753.00,
		"xiao":84,
		"contents":632,
		"id":1262,
		"url":"http://s.handu.com/images/201605/thumb_img/1463256640144256437.jpg"
	},{
		"name":"韩都衣舍2016秋装韩版百搭",
		"price":634.00,
		"xiao":786,
		"contents":46,
		"id":1263,
		"url":"http://s.handu.com/images/201707/thumb_img/1501272704936123358.jpg"
	},{
		"name":"韩都衣舍2016秋装韩版百搭",
		"price":754.00,
		"xiao":87,
		"contents":85,
		"id":1264,
		"url":"http://s.handu.com/images/201704/thumb_img/1491855095200850057.jpg"
	},{
		"name":"韩都衣舍2016秋装韩版百搭",
		"price":756.00,
		"xiao":81,
		"contents":70,
		"id":1265,
		"url":"http://s.handu.com/images/201709/thumb_img/1504728715928758501.jpg"
	},{
		"name":"韩都衣舍2016秋装韩版百搭",
		"price":34.00,
		"xiao":54,
		"contents":62,
		"id":1251,
		"url":"http://s.handu.com/images/201709/thumb_img/1504296632127681400.jpg"
	},{
		"name":"韩都衣舍2016秋装韩版百搭",
		"price":466.00,
		"xiao":573,
		"contents":452,
		"id":1252,
		"url":"http://s.handu.com/images/201704/thumb_img/1493323811451973072.jpg"
	},{
		"name":"韩都衣舍2016秋装韩版百搭",
		"price":342.00,
		"xiao":15,
		"contents":54,
		"id":1253,
		"url":"http://s.handu.com/images/201703/thumb_img/1488312649709027465.jpg"
	},{
		"name":"韩都衣舍2016秋装韩版百搭",
		"price":654.00,
		"xiao":74,
		"contents":51,
		"id":1254,
		"url":"http://s.handu.com/images/201708/thumb_img/1503432633419544649.jpg"
	},{
		"name":"韩都衣舍2016秋装韩版百搭",
		"price":634.00,
		"xiao":654,
		"contents":62,
		"id":1255,
		"url":"http://s.handu.com/images/201707/thumb_img/1501272663150993279.jpg"
	},{
		"name":"韩都衣舍2016秋装韩版百搭",
		"price":35.00,
		"xiao":25,
		"contents":753,
		"id":1256,
		"url":"http://s.handu.com/images/201605/thumb_img/1463343062523682099.jpg"
	},{
		"name":"韩都衣舍2016秋装韩版百搭",
		"price":35.00,
		"xiao":64,
		"contents":73,
		"id":1257,
		"url":"http://s.handu.com/images/201704/thumb_img/1490991015662929093.jpg"
	},{
		"name":"韩都衣舍2016秋装韩版百搭",
		"price":633.00,
		"xiao":26,
		"contents":64,
		"id":1258,
		"url":"http://s.handu.com/images/201608/thumb_img/1470773466136458946.jpg"
	},{
		"name":"韩都衣舍2016秋装韩版百搭",
		"price":25.00,
		"xiao":3643,
		"contents":75,
		"id":1259,
		"url":"http://s.handu.com/images/201608/thumb_img/1471551063625516912.jpg"
	},{
		"name":"韩都衣舍2016秋装韩版百搭",
		"price":57.00,
		"xiao":73,
		"contents":95,
		"id":1260,
		"url":"http://s.handu.com/images/201704/thumb_img/1493323818699400872.jpg"
	},{
		"name":"韩都衣舍2016秋装韩版百搭",
		"price":537.00,
		"xiao":64,
		"contents":86,
		"id":1261,
		"url":"http://s.handu.com/images/201709/thumb_img/1506715840076015143.jpg"
	},{
		"name":"韩都衣舍2016秋装韩版百搭",
		"price":753.00,
		"xiao":84,
		"contents":632,
		"id":1262,
		"url":"http://s.handu.com/images/201605/thumb_img/1463256640144256437.jpg"
	},{
		"name":"韩都衣舍2016秋装韩版百搭",
		"price":634.00,
		"xiao":786,
		"contents":46,
		"id":1263,
		"url":"http://s.handu.com/images/201707/thumb_img/1501272704936123358.jpg"
	},{
		"name":"韩都衣舍2016秋装韩版百搭",
		"price":754.00,
		"xiao":87,
		"contents":85,
		"id":1264,
		"url":"http://s.handu.com/images/201704/thumb_img/1491855095200850057.jpg"
	},{
		"name":"韩都衣舍2016秋装韩版百搭",
		"price":756.00,
		"xiao":81,
		"contents":70,
		"id":1265,
		"url":"http://s.handu.com/images/201709/thumb_img/1504728715928758501.jpg"
	},{
		"name":"韩都衣舍2016秋装韩版百搭",
		"price":805.00,
		"xiao":70,
		"contents":3,
		"id":1266,		
		"url":"http://s.handu.com/images/201609/thumb_img/1046131_thumb_G_1473843851049.jpg"
	},{
		"name":"韩都衣舍2016秋装韩版百搭",
		"price":675.00,
		"xiao":746,
		"contents":678,
		"id":1267,
		"url":"http://s.handu.com/images/201708/thumb_img/1502395837350264937.jpg"
	},{
		"name":"韩都衣舍2016秋装韩版百搭",
		"price":466.00,
		"xiao":573,
		"contents":452,
		"id":1252,
		"url":"http://s.handu.com/images/201704/thumb_img/1493323811451973072.jpg"
	},{
		"name":"韩都衣舍2016秋装韩版百搭",
		"price":342.00,
		"xiao":15,
		"contents":54,
		"id":1253,
		"url":"http://s.handu.com/images/201703/thumb_img/1488312649709027465.jpg"
	},{
		"name":"韩都衣舍2016秋装韩版百搭",
		"price":654.00,
		"xiao":74,
		"contents":51,
		"id":1254,
		"url":"http://s.handu.com/images/201708/thumb_img/1503432633419544649.jpg"
	},{
		"name":"韩都衣舍2016秋装韩版百搭",
		"price":634.00,
		"xiao":654,
		"contents":62,
		"id":1255,
		"url":"http://s.handu.com/images/201707/thumb_img/1501272663150993279.jpg"
	},{
		"name":"韩都衣舍2016秋装韩版百搭",
		"price":35.00,
		"xiao":25,
		"contents":753,
		"id":1256,
		"url":"http://s.handu.com/images/201605/thumb_img/1463343062523682099.jpg"
	},{
		"name":"韩都衣舍2016秋装韩版百搭",
		"price":35.00,
		"xiao":64,
		"contents":73,
		"id":1257,
		"url":"http://s.handu.com/images/201704/thumb_img/1490991015662929093.jpg"
	},{
		"name":"韩都衣舍2016秋装韩版百搭",
		"price":633.00,
		"xiao":26,
		"contents":64,
		"id":1258,
		"url":"http://s.handu.com/images/201608/thumb_img/1470773466136458946.jpg"
	},{
		"name":"韩都衣舍2016秋装韩版百搭",
		"price":25.00,
		"xiao":3643,
		"contents":75,
		"id":1259,
		"url":"http://s.handu.com/images/201608/thumb_img/1471551063625516912.jpg"
	},{
		"name":"韩都衣舍2016秋装韩版百搭",
		"price":754.00,
		"xiao":87,
		"contents":85,
		"id":1264,
		"url":"http://s.handu.com/images/201704/thumb_img/1491855095200850057.jpg"
	},{
		"name":"韩都衣舍2016秋装韩版百搭",
		"price":756.00,
		"xiao":81,
		"contents":70,
		"id":1265,
		"url":"http://s.handu.com/images/201709/thumb_img/1504728715928758501.jpg"
	},{
		"name":"韩都衣舍2016秋装韩版百搭",
		"price":805.00,
		"xiao":70,
		"contents":3,
		"id":1266,		
		"url":"http://s.handu.com/images/201609/thumb_img/1046131_thumb_G_1473843851049.jpg"
	},{
		"name":"韩都衣舍2016秋装韩版百搭",
		"price":675.00,
		"xiao":746,
		"contents":678,
		"id":1267,
		"url":"http://s.handu.com/images/201708/thumb_img/1502395837350264937.jpg"
	},{
		"name":"韩都衣舍2016秋装韩版百搭",
		"price":466.00,
		"xiao":573,
		"contents":452,
		"id":1252,
		"url":"http://s.handu.com/images/201704/thumb_img/1493323811451973072.jpg"
	},{
		"name":"韩都衣舍2016秋装韩版百搭",
		"price":342.00,
		"xiao":15,
		"contents":54,
		"id":1253,
		"url":"http://s.handu.com/images/201703/thumb_img/1488312649709027465.jpg"
	},{
		"name":"韩都衣舍2016秋装韩版百搭",
		"price":654.00,
		"xiao":74,
		"contents":51,
		"id":1254,
		"url":"http://s.handu.com/images/201708/thumb_img/1503432633419544649.jpg"
	},{
		"name":"韩都衣舍2016秋装韩版百搭",
		"price":634.00,
		"xiao":654,
		"contents":62,
		"id":1255,
		"url":"http://s.handu.com/images/201707/thumb_img/1501272663150993279.jpg"
	},{
		"name":"韩都衣舍2016秋装韩版百搭",
		"price":86.00,
		"xiao":743,
		"contents":295,
		"id":1268,
		"url":"http://s.handu.com/images/201709/thumb_img/1506715838430079469.jpg"
	},{
		"name":"韩都衣舍2016秋装韩版百搭",
		"price":754.00,
		"xiao":35,
		"contents":63,
		"id":1269,
		"url":"http://s.handu.com/images/201707/thumb_img/1499199060080994589.jpg"
	},{
		"name":"韩都衣舍2016秋装韩版百搭",
		"price":531.00,
		"xiao":62,
		"contents":26,
		"id":1270,
		"url":"http://s.handu.com/images/201707/thumb_img/1500862591671331961.jpg"
	},{
		"name":"韩都衣舍2016秋装韩版百搭",
		"price":531.00,
		"xiao":62,
		"contents":26,
		"id":1270,
		"url":"http://s.handu.com/images/201707/thumb_img/1500862591671331961.jpg"
	},{
		"name":"韩都衣舍2016秋装韩版百搭",
		"price":57.00,
		"xiao":73,
		"contents":95,
		"id":1260,
		"url":"http://s.handu.com/images/201704/thumb_img/1493323818699400872.jpg"
	},{
		"name":"韩都衣舍2016秋装韩版百搭",
		"price":537.00,
		"xiao":64,
		"contents":86,
		"id":1261,
		"url":"http://s.handu.com/images/201709/thumb_img/1506715840076015143.jpg"
	},{
		"name":"韩都衣舍2016秋装韩版百搭",
		"price":753.00,
		"xiao":84,
		"contents":632,
		"id":1262,
		"url":"http://s.handu.com/images/201605/thumb_img/1463256640144256437.jpg"
	},{
		"name":"韩都衣舍2016秋装韩版百搭",
		"price":634.00,
		"xiao":786,
		"contents":46,
		"id":1263,
		"url":"http://s.handu.com/images/201707/thumb_img/1501272704936123358.jpg"
	},{
		"name":"韩都衣舍2016秋装韩版百搭",
		"price":754.00,
		"xiao":87,
		"contents":85,
		"id":1264,
		"url":"http://s.handu.com/images/201704/thumb_img/1491855095200850057.jpg"
	},{
		"name":"韩都衣舍2016秋装韩版百搭",
		"price":756.00,
		"xiao":81,
		"contents":70,
		"id":1265,
		"url":"http://s.handu.com/images/201709/thumb_img/1504728715928758501.jpg"
	},{
		"name":"韩都衣舍2016秋装韩版百搭",
		"price":756.00,
		"xiao":81,
		"contents":70,
		"id":1265,
		"url":"http://s.handu.com/images/201709/thumb_img/1504728715928758501.jpg"
	},{
		"name":"韩都衣舍2016秋装韩版百搭",
		"price":34.00,
		"xiao":54,
		"contents":62,
		"id":1251,
		"url":"http://s.handu.com/images/201709/thumb_img/1504296632127681400.jpg"
	},{
		"name":"韩都衣舍2016秋装韩版百搭",
		"price":466.00,
		"xiao":573,
		"contents":452,
		"id":1252,
		"url":"http://s.handu.com/images/201704/thumb_img/1493323811451973072.jpg"
	},{
		"name":"韩都衣舍2016秋装韩版百搭",
		"price":342.00,
		"xiao":15,
		"contents":54,
		"id":1253,
		"url":"http://s.handu.com/images/201703/thumb_img/1488312649709027465.jpg"
	},{
		"name":"韩都衣舍2016秋装韩版百搭",
		"price":654.00,
		"xiao":74,
		"contents":51,
		"id":1254,
		"url":"http://s.handu.com/images/201708/thumb_img/1503432633419544649.jpg"
	},{
		"name":"韩都衣舍2016秋装韩版百搭",
		"price":634.00,
		"xiao":654,
		"contents":62,
		"id":1255,
		"url":"http://s.handu.com/images/201707/thumb_img/1501272663150993279.jpg"
	},{
		"name":"韩都衣舍2016秋装韩版百搭",
		"price":35.00,
		"xiao":25,
		"contents":753,
		"id":1256,
		"url":"http://s.handu.com/images/201605/thumb_img/1463343062523682099.jpg"
	},{
		"name":"韩都衣舍2016秋装韩版百搭",
		"price":35.00,
		"xiao":64,
		"contents":73,
		"id":1257,
		"url":"http://s.handu.com/images/201704/thumb_img/1490991015662929093.jpg"
	},{
		"name":"韩都衣舍2016秋装韩版百搭",
		"price":633.00,
		"xiao":26,
		"contents":64,
		"id":1258,
		"url":"http://s.handu.com/images/201608/thumb_img/1470773466136458946.jpg"
	},{
		"name":"韩都衣舍2016秋装韩版百搭",
		"price":25.00,
		"xiao":3643,
		"contents":75,
		"id":1259,
		"url":"http://s.handu.com/images/201608/thumb_img/1471551063625516912.jpg"
	},{
		"name":"韩都衣舍2016秋装韩版百搭",
		"price":57.00,
		"xiao":73,
		"contents":95,
		"id":1260,
		"url":"http://s.handu.com/images/201704/thumb_img/1493323818699400872.jpg"
	},{
		"name":"韩都衣舍2016秋装韩版百搭",
		"price":537.00,
		"xiao":64,
		"contents":86,
		"id":1261,
		"url":"http://s.handu.com/images/201709/thumb_img/1506715840076015143.jpg"
	},{
		"name":"韩都衣舍2016秋装韩版百搭",
		"price":753.00,
		"xiao":84,
		"contents":632,
		"id":1262,
		"url":"http://s.handu.com/images/201605/thumb_img/1463256640144256437.jpg"
	},{
		"name":"韩都衣舍2016秋装韩版百搭",
		"price":634.00,
		"xiao":786,
		"contents":46,
		"id":1263,
		"url":"http://s.handu.com/images/201707/thumb_img/1501272704936123358.jpg"
	},{
		"name":"韩都衣舍2016秋装韩版百搭",
		"price":754.00,
		"xiao":87,
		"contents":85,
		"id":1264,
		"url":"http://s.handu.com/images/201704/thumb_img/1491855095200850057.jpg"
	},{
		"name":"韩都衣舍2016秋装韩版百搭",
		"price":756.00,
		"xiao":81,
		"contents":70,
		"id":1265,
		"url":"http://s.handu.com/images/201709/thumb_img/1504728715928758501.jpg"
	},{
		"name":"韩都衣舍2016秋装韩版百搭",
		"price":805.00,
		"xiao":70,
		"contents":3,
		"id":1266,		
		"url":"http://s.handu.com/images/201609/thumb_img/1046131_thumb_G_1473843851049.jpg"
	},{
		"name":"韩都衣舍2016秋装韩版百搭",
		"price":675.00,
		"xiao":746,
		"contents":678,
		"id":1267,
		"url":"http://s.handu.com/images/201708/thumb_img/1502395837350264937.jpg"
	},{
		"name":"韩都衣舍2016秋装韩版百搭",
		"price":466.00,
		"xiao":573,
		"contents":452,
		"id":1252,
		"url":"http://s.handu.com/images/201704/thumb_img/1493323811451973072.jpg"
	},{
		"name":"韩都衣舍2016秋装韩版百搭",
		"price":342.00,
		"xiao":15,
		"contents":54,
		"id":1253,
		"url":"http://s.handu.com/images/201703/thumb_img/1488312649709027465.jpg"
	},{
		"name":"韩都衣舍2016秋装韩版百搭",
		"price":438.00,
		"xiao":323,
		"contents":223,
		"id":1232,
		"url":"http://s.handu.com/images/201709/thumb_img/1504987885123513412.jpg"
	},{
		"name":"韩都衣舍2016秋装韩版百搭",
		"price":48.00,
		"xiao":433,
		"contents":63,
		"id":1233,
		"url":"http://s.handu.com/images/201610/thumb_img/1477858289891674986.jpg"
	},{
		"name":"韩都衣舍2016秋装韩版百搭",
		"price":38.00,
		"xiao":32,
		"contents":73,
		"id":1234,
		"url":"http://s.handu.com/images/201607/thumb_img/1468527019657514084.jpg"
	},{
		"name":"韩都衣舍2016秋装韩版百搭",
		"price":4375.00,
		"xiao":33,
		"contents":27,
		"id":1235,
		"url":"http://s.handu.com/images/201605/thumb_img/1463256647982189429.jpg"
	},{
		"name":"韩都衣舍2016秋装韩版百搭",
		"price":98.00,
		"xiao":433,
		"contents":83,
		"id":1236,
		"url":"http://s.handu.com/images/201708/thumb_img/1503432636679267622.jpg"
	},{
		"name":"韩都衣舍2016秋装韩版百搭",
		"price":538.00,
		"xiao":3123,
		"contents":343,
		"id":1237,
		"url":"http://s.handu.com/images/201603/thumb_img/1459282501117262858.jpg"
	},{
		"name":"韩都衣舍2016秋装韩版百搭",
		"price":428.00,
		"xiao":63,
		"contents":133,
		"id":1238,
		"url":"http://s.handu.com/images/201703/thumb_img/1490472629482950873.jpg"
	},{
		"name":"韩都衣舍2016秋装韩版百搭",
		"price":138.00,
		"xiao":35,
		"contents":64,
		"id":1239,
		"url":"http://s.handu.com/images/201612/thumb_img/1480709466420407678.jpg"
	},{
		"name":"韩都衣舍2016秋装韩版百搭",
		"price":24.00,
		"xiao":335,
		"contents":223,
		"id":1240,
		"url":"http://s.handu.com/images/201703/thumb_img/1056203_thumb_G_1490252555160.jpg"
	},{
		"name":"韩都衣舍2016秋装韩版百搭",
		"price":3258.00,
		"xiao":3323,
		"contents":123,
		"id":1241,
		"url":"http://s.handu.com/images/201709/thumb_img/1504296651432586671.jpg"
	},{
		"name":"韩都衣舍2016秋装韩版百搭",
		"price":538.00,
		"xiao":3123,
		"contents":27,
		"id":1242,
		"url":"http://s.handu.com/images/201707/thumb_img/1501272612540619861.jpg"
	},{
		"name":"韩都衣舍2016秋装韩版百搭",
		"price":434.00,
		"xiao":312,
		"contents":245,
		"id":1243,
		"url":"http://s.handu.com/images/201705/thumb_img/1495138402759096558.jpg"
	},{
		"name":"韩都衣舍2016秋装韩版百搭",
		"price":432.00,
		"xiao":365,
		"contents":212,
		"id":1234,
		"url":"http://s.handu.com/images/201708/thumb_img/1503432660825646787.jpg"
	},{
		"name":"韩都衣舍2016秋装韩版百搭",
		"price":4325.00,
		"xiao":34,
		"contents":43,
		"id":1245,
		"url":"http://s.handu.com/images/201703/thumb_img/1489781417259079571.jpg"
	},{
		"name":"韩都衣舍2016秋装韩版百搭",
		"price":543.00,
		"xiao":3123,
		"contents":56,
		"id":1246,
		"url":"http://s.handu.com/images/201709/thumb_img/1506715838430079469.jpg"
	},{
		"name":"韩都衣舍2016秋装韩版百搭",
		"price":79.00,
		"xiao":86,
		"contents":75,
		"id":1247,
		"url":"http://s.handu.com/images/201709/thumb_img/1506024659288448285.jpg"
	},{
		"name":"韩都衣舍2016秋装韩版百搭",
		"price":478.00,
		"xiao":34,
		"contents":765,
		"id":1248,
		"url":"http://s.handu.com/images/201703/thumb_img/1489695045135412556.jpg"
	},{
		"name":"韩都衣舍2016秋装韩版百搭",
		"price":565.00,
		"xiao":345,
		"contents":786,
		"id":1249,
		"url":"http://s.handu.com/images/201708/thumb_img/1502568628263654127.jpg"
	},{
		"name":"韩都衣舍2016秋装韩版百搭",
		"price":467.00,
		"xiao":472,
		"contents":83,
		"id":1250,
		"url":"http://s.handu.com/images/201709/thumb_img/1504383010349786942.jpg"
	},{
		"name":"韩都衣舍2016秋装韩版百搭",
		"price":34.00,
		"xiao":54,
		"contents":62,
		"id":1251,
		"url":"http://s.handu.com/images/201709/thumb_img/1504296632127681400.jpg"
	},{
		"name":"韩都衣舍2016秋装韩版百搭",
		"price":466.00,
		"xiao":573,
		"contents":452,
		"id":1252,
		"url":"http://s.handu.com/images/201704/thumb_img/1493323811451973072.jpg"
	},{
		"name":"韩都衣舍2016秋装韩版百搭",
		"price":342.00,
		"xiao":15,
		"contents":54,
		"id":1253,
		"url":"http://s.handu.com/images/201703/thumb_img/1488312649709027465.jpg"
	},{
		"name":"韩都衣舍2016秋装韩版百搭",
		"price":654.00,
		"xiao":74,
		"contents":51,
		"id":1254,
		"url":"http://s.handu.com/images/201708/thumb_img/1503432633419544649.jpg"
	},{
		"name":"韩都衣舍2016秋装韩版百搭",
		"price":634.00,
		"xiao":654,
		"contents":62,
		"id":1255,
		"url":"http://s.handu.com/images/201707/thumb_img/1501272663150993279.jpg"
	},{
		"name":"韩都衣舍2016秋装韩版百搭",
		"price":35.00,
		"xiao":25,
		"contents":753,
		"id":1256,
		"url":"http://s.handu.com/images/201605/thumb_img/1463343062523682099.jpg"
	},{
		"name":"韩都衣舍2016秋装韩版百搭",
		"price":35.00,
		"xiao":64,
		"contents":73,
		"id":1257,
		"url":"http://s.handu.com/images/201704/thumb_img/1490991015662929093.jpg"
	},{
		"name":"韩都衣舍2016秋装韩版百搭",
		"price":633.00,
		"xiao":26,
		"contents":64,
		"id":1258,
		"url":"http://s.handu.com/images/201608/thumb_img/1470773466136458946.jpg"
	},{
		"name":"韩都衣舍2016秋装韩版百搭",
		"price":25.00,
		"xiao":3643,
		"contents":75,
		"id":1259,
		"url":"http://s.handu.com/images/201608/thumb_img/1471551063625516912.jpg"
	},{
		"name":"韩都衣舍2016秋装韩版百搭",
		"price":57.00,
		"xiao":73,
		"contents":95,
		"id":1260,
		"url":"http://s.handu.com/images/201704/thumb_img/1493323818699400872.jpg"
	},{
		"name":"韩都衣舍2016秋装韩版百搭",
		"price":537.00,
		"xiao":64,
		"contents":86,
		"id":1261,
		"url":"http://s.handu.com/images/201709/thumb_img/1506715840076015143.jpg"
	},{
		"name":"韩都衣舍2016秋装韩版百搭",
		"price":753.00,
		"xiao":84,
		"contents":632,
		"id":1262,
		"url":"http://s.handu.com/images/201605/thumb_img/1463256640144256437.jpg"
	},{
		"name":"韩都衣舍2016秋装韩版百搭",
		"price":634.00,
		"xiao":786,
		"contents":46,
		"id":1263,
		"url":"http://s.handu.com/images/201707/thumb_img/1501272704936123358.jpg"
	},{
		"name":"韩都衣舍2016秋装韩版百搭",
		"price":754.00,
		"xiao":87,
		"contents":85,
		"id":1264,
		"url":"http://s.handu.com/images/201704/thumb_img/1491855095200850057.jpg"
	},{
		"name":"韩都衣舍2016秋装韩版百搭",
		"price":756.00,
		"xiao":81,
		"contents":70,
		"id":1265,
		"url":"http://s.handu.com/images/201709/thumb_img/1504728715928758501.jpg"
	},{
		"name":"韩都衣舍2016秋装韩版百搭",
		"price":805.00,
		"xiao":70,
		"contents":3,
		"id":1266,		
		"url":"http://s.handu.com/images/201609/thumb_img/1046131_thumb_G_1473843851049.jpg"
	},{
		"name":"韩都衣舍2016秋装韩版百搭",
		"price":675.00,
		"xiao":746,
		"contents":678,
		"id":1267,
		"url":"http://s.handu.com/images/201708/thumb_img/1502395837350264937.jpg"
	},{
		"name":"韩都衣舍2016秋装韩版百搭",
		"price":86.00,
		"xiao":743,
		"contents":295,
		"id":1268,
		"url":"http://s.handu.com/images/201709/thumb_img/1506715838430079469.jpg"
	},{
		"name":"韩都衣舍2016秋装韩版百搭",
		"price":754.00,
		"xiao":35,
		"contents":63,
		"id":1269,
		"url":"http://s.handu.com/images/201707/thumb_img/1499199060080994589.jpg"
	},{
		"name":"韩都衣舍2016秋装韩版百搭",
		"price":531.00,
		"xiao":62,
		"contents":26,
		"id":1270,
		"url":"http://s.handu.com/images/201707/thumb_img/1500862591671331961.jpg"
	},{
		"name":"韩都衣舍2016秋装韩版百搭",
		"price":531.00,
		"xiao":62,
		"contents":26,
		"id":1270,
		"url":"http://s.handu.com/images/201707/thumb_img/1500862591671331961.jpg"
	},{
		"name":"韩都衣舍2016秋装韩版百搭",
		"price":57.00,
		"xiao":73,
		"contents":95,
		"id":1260,
		"url":"http://s.handu.com/images/201704/thumb_img/1493323818699400872.jpg"
	},{
		"name":"韩都衣舍2016秋装韩版百搭",
		"price":537.00,
		"xiao":64,
		"contents":86,
		"id":1261,
		"url":"http://s.handu.com/images/201709/thumb_img/1506715840076015143.jpg"
	},{
		"name":"韩都衣舍2016秋装韩版百搭",
		"price":753.00,
		"xiao":84,
		"contents":632,
		"id":1262,
		"url":"http://s.handu.com/images/201605/thumb_img/1463256640144256437.jpg"
	},{
		"name":"韩都衣舍2016秋装韩版百搭",
		"price":634.00,
		"xiao":786,
		"contents":46,
		"id":1263,
		"url":"http://s.handu.com/images/201707/thumb_img/1501272704936123358.jpg"
	},{
		"name":"韩都衣舍2016秋装韩版百搭",
		"price":754.00,
		"xiao":87,
		"contents":85,
		"id":1264,
		"url":"http://s.handu.com/images/201704/thumb_img/1491855095200850057.jpg"
	},{
		"name":"韩都衣舍2016秋装韩版百搭",
		"price":756.00,
		"xiao":81,
		"contents":70,
		"id":1265,
		"url":"http://s.handu.com/images/201709/thumb_img/1504728715928758501.jpg"
	},{
		"name":"韩都衣舍2016秋装韩版百搭",
		"price":805.00,
		"xiao":70,
		"contents":3,
		"id":1266,		
		"url":"http://s.handu.com/images/201609/thumb_img/1046131_thumb_G_1473843851049.jpg"
	},{
		"name":"韩都衣舍2016秋装韩版百搭",
		"price":675.00,
		"xiao":746,
		"contents":678,
		"id":1267,
		"url":"http://s.handu.com/images/201708/thumb_img/1502395837350264937.jpg"
	},{
		"name":"韩都衣舍2016秋装韩版百搭",
		"price":86.00,
		"xiao":743,
		"contents":295,
		"id":1268,
		"url":"http://s.handu.com/images/201709/thumb_img/1506715838430079469.jpg"
	},{
		"name":"韩都衣舍2016秋装韩版百搭",
		"price":754.00,
		"xiao":35,
		"contents":63,
		"id":1269,
		"url":"http://s.handu.com/images/201707/thumb_img/1499199060080994589.jpg"
	},{
		"name":"韩都衣舍2016秋装韩版百搭",
		"price":531.00,
		"xiao":62,
		"contents":26,
		"id":1270,
		"url":"http://s.handu.com/images/201707/thumb_img/1500862591671331961.jpg"
	},{
		"name":"韩都衣舍2016秋装韩版百搭",
		"price":531.00,
		"xiao":62,
		"contents":26,
		"id":1270,
		"url":"http://s.handu.com/images/201707/thumb_img/1500862591671331961.jpg"
	},{
		"name":"韩都衣舍2016秋装韩版百搭",
		"price":805.00,
		"xiao":70,
		"contents":3,
		"id":1266,		
		"url":"http://s.handu.com/images/201609/thumb_img/1046131_thumb_G_1473843851049.jpg"
	},{
		"name":"韩都衣舍2016秋装韩版百搭",
		"price":675.00,
		"xiao":746,
		"contents":678,
		"id":1267,
		"url":"http://s.handu.com/images/201708/thumb_img/1502395837350264937.jpg"
	},{
		"name":"韩都衣舍2016秋装韩版百搭",
		"price":86.00,
		"xiao":743,
		"contents":295,
		"id":1268,
		"url":"http://s.handu.com/images/201709/thumb_img/1506715838430079469.jpg"
	},{
		"name":"韩都衣舍2016秋装韩版百搭",
		"price":754.00,
		"xiao":35,
		"contents":63,
		"id":1269,
		"url":"http://s.handu.com/images/201707/thumb_img/1499199060080994589.jpg"
	},{
		"name":"韩都衣舍2016秋装韩版百搭",
		"price":531.00,
		"xiao":62,
		"contents":26,
		"id":1270,
		"url":"http://s.handu.com/images/201707/thumb_img/1500862591671331961.jpg"
	},{
		"name":"韩都衣舍2016秋装韩版百搭",
		"price":531.00,
		"xiao":62,
		"contents":26,
		"id":1270,
		"url":"http://s.handu.com/images/201707/thumb_img/1500862591671331961.jpg"
	},{
		"name":"韩都衣舍2016秋装韩版百搭",
		"price":57.00,
		"xiao":73,
		"contents":95,
		"id":1260,
		"url":"http://s.handu.com/images/201704/thumb_img/1493323818699400872.jpg"
	},{
		"name":"韩都衣舍2016秋装韩版百搭",
		"price":537.00,
		"xiao":64,
		"contents":86,
		"id":1261,
		"url":"http://s.handu.com/images/201709/thumb_img/1506715840076015143.jpg"
	},{
		"name":"韩都衣舍2016秋装韩版百搭",
		"price":753.00,
		"xiao":84,
		"contents":632,
		"id":1262,
		"url":"http://s.handu.com/images/201605/thumb_img/1463256640144256437.jpg"
	},{
		"name":"韩都衣舍2016秋装韩版百搭",
		"price":634.00,
		"xiao":786,
		"contents":46,
		"id":1263,
		"url":"http://s.handu.com/images/201707/thumb_img/1501272704936123358.jpg"
	},{
		"name":"韩都衣舍2016秋装韩版百搭",
		"price":754.00,
		"xiao":87,
		"contents":85,
		"id":1264,
		"url":"http://s.handu.com/images/201704/thumb_img/1491855095200850057.jpg"
	},{
		"name":"韩都衣舍2016秋装韩版百搭",
		"price":756.00,
		"xiao":81,
		"contents":70,
		"id":1265,
		"url":"http://s.handu.com/images/201709/thumb_img/1504728715928758501.jpg"
	},{
		"name":"韩都衣舍2016秋装韩版百搭",
		"price":34.00,
		"xiao":54,
		"contents":62,
		"id":1251,
		"url":"http://s.handu.com/images/201709/thumb_img/1504296632127681400.jpg"
	},{
		"name":"韩都衣舍2016秋装韩版百搭",
		"price":466.00,
		"xiao":573,
		"contents":452,
		"id":1252,
		"url":"http://s.handu.com/images/201704/thumb_img/1493323811451973072.jpg"
	},{
		"name":"韩都衣舍2016秋装韩版百搭",
		"price":342.00,
		"xiao":15,
		"contents":54,
		"id":1253,
		"url":"http://s.handu.com/images/201703/thumb_img/1488312649709027465.jpg"
	},{
		"name":"韩都衣舍2016秋装韩版百搭",
		"price":654.00,
		"xiao":74,
		"contents":51,
		"id":1254,
		"url":"http://s.handu.com/images/201708/thumb_img/1503432633419544649.jpg"
	},{
		"name":"韩都衣舍2016秋装韩版百搭",
		"price":634.00,
		"xiao":654,
		"contents":62,
		"id":1255,
		"url":"http://s.handu.com/images/201707/thumb_img/1501272663150993279.jpg"
	},{
		"name":"韩都衣舍2016秋装韩版百搭",
		"price":35.00,
		"xiao":25,
		"contents":753,
		"id":1256,
		"url":"http://s.handu.com/images/201605/thumb_img/1463343062523682099.jpg"
	},{
		"name":"韩都衣舍2016秋装韩版百搭",
		"price":35.00,
		"xiao":64,
		"contents":73,
		"id":1257,
		"url":"http://s.handu.com/images/201704/thumb_img/1490991015662929093.jpg"
	},{
		"name":"韩都衣舍2016秋装韩版百搭",
		"price":633.00,
		"xiao":26,
		"contents":64,
		"id":1258,
		"url":"http://s.handu.com/images/201608/thumb_img/1470773466136458946.jpg"
	},{
		"name":"韩都衣舍2016秋装韩版百搭",
		"price":25.00,
		"xiao":3643,
		"contents":75,
		"id":1259,
		"url":"http://s.handu.com/images/201608/thumb_img/1471551063625516912.jpg"
	},{
		"name":"韩都衣舍2016秋装韩版百搭",
		"price":57.00,
		"xiao":73,
		"contents":95,
		"id":1260,
		"url":"http://s.handu.com/images/201704/thumb_img/1493323818699400872.jpg"
	},{
		"name":"韩都衣舍2016秋装韩版百搭",
		"price":537.00,
		"xiao":64,
		"contents":86,
		"id":1261,
		"url":"http://s.handu.com/images/201709/thumb_img/1506715840076015143.jpg"
	},{
		"name":"韩都衣舍2016秋装韩版百搭",
		"price":753.00,
		"xiao":84,
		"contents":632,
		"id":1262,
		"url":"http://s.handu.com/images/201605/thumb_img/1463256640144256437.jpg"
	},{
		"name":"韩都衣舍2016秋装韩版百搭",
		"price":634.00,
		"xiao":786,
		"contents":46,
		"id":1263,
		"url":"http://s.handu.com/images/201707/thumb_img/1501272704936123358.jpg"
	},{
		"name":"韩都衣舍2016秋装韩版百搭",
		"price":754.00,
		"xiao":87,
		"contents":85,
		"id":1264,
		"url":"http://s.handu.com/images/201704/thumb_img/1491855095200850057.jpg"
	},{
		"name":"韩都衣舍2016秋装韩版百搭",
		"price":756.00,
		"xiao":81,
		"contents":70,
		"id":1265,
		"url":"http://s.handu.com/images/201709/thumb_img/1504728715928758501.jpg"
	},{
		"name":"韩都衣舍2016秋装韩版百搭",
		"price":805.00,
		"xiao":70,
		"contents":3,
		"id":1266,		
		"url":"http://s.handu.com/images/201609/thumb_img/1046131_thumb_G_1473843851049.jpg"
	},{
		"name":"韩都衣舍2016秋装韩版百搭",
		"price":675.00,
		"xiao":746,
		"contents":678,
		"id":1267,
		"url":"http://s.handu.com/images/201708/thumb_img/1502395837350264937.jpg"
	},{
		"name":"韩都衣舍2016秋装韩版百搭",
		"price":466.00,
		"xiao":573,
		"contents":452,
		"id":1252,
		"url":"http://s.handu.com/images/201704/thumb_img/1493323811451973072.jpg"
	},{
		"name":"韩都衣舍2016秋装韩版百搭",
		"price":438.00,
		"xiao":323,
		"contents":223,
		"id":1232,
		"url":"http://s.handu.com/images/201709/thumb_img/1504987885123513412.jpg"
	},{
		"name":"韩都衣舍2016秋装韩版百搭",
		"price":48.00,
		"xiao":433,
		"contents":63,
		"id":1233,
		"url":"http://s.handu.com/images/201610/thumb_img/1477858289891674986.jpg"
	},{
		"name":"韩都衣舍2016秋装韩版百搭",
		"price":38.00,
		"xiao":32,
		"contents":73,
		"id":1234,
		"url":"http://s.handu.com/images/201607/thumb_img/1468527019657514084.jpg"
	},{
		"name":"韩都衣舍2016秋装韩版百搭",
		"price":4375.00,
		"xiao":33,
		"contents":27,
		"id":1235,
		"url":"http://s.handu.com/images/201605/thumb_img/1463256647982189429.jpg"
	},{
		"name":"韩都衣舍2016秋装韩版百搭",
		"price":98.00,
		"xiao":433,
		"contents":83,
		"id":1236,
		"url":"http://s.handu.com/images/201708/thumb_img/1503432636679267622.jpg"
	},{
		"name":"韩都衣舍2016秋装韩版百搭",
		"price":538.00,
		"xiao":3123,
		"contents":343,
		"id":1237,
		"url":"http://s.handu.com/images/201603/thumb_img/1459282501117262858.jpg"
	},{
		"name":"韩都衣舍2016秋装韩版百搭",
		"price":428.00,
		"xiao":63,
		"contents":133,
		"id":1238,
		"url":"http://s.handu.com/images/201703/thumb_img/1490472629482950873.jpg"
	},{
		"name":"韩都衣舍2016秋装韩版百搭",
		"price":138.00,
		"xiao":35,
		"contents":64,
		"id":1239,
		"url":"http://s.handu.com/images/201612/thumb_img/1480709466420407678.jpg"
	},{
		"name":"韩都衣舍2016秋装韩版百搭",
		"price":24.00,
		"xiao":335,
		"contents":223,
		"id":1240,
		"url":"http://s.handu.com/images/201703/thumb_img/1056203_thumb_G_1490252555160.jpg"
	},{
		"name":"韩都衣舍2016秋装韩版百搭",
		"price":3258.00,
		"xiao":3323,
		"contents":123,
		"id":1241,
		"url":"http://s.handu.com/images/201709/thumb_img/1504296651432586671.jpg"
	},{
		"name":"韩都衣舍2016秋装韩版百搭",
		"price":538.00,
		"xiao":3123,
		"contents":27,
		"id":1242,
		"url":"http://s.handu.com/images/201707/thumb_img/1501272612540619861.jpg"
	},{
		"name":"韩都衣舍2016秋装韩版百搭",
		"price":434.00,
		"xiao":312,
		"contents":245,
		"id":1243,
		"url":"http://s.handu.com/images/201705/thumb_img/1495138402759096558.jpg"
	},{
		"name":"韩都衣舍2016秋装韩版百搭",
		"price":432.00,
		"xiao":365,
		"contents":212,
		"id":1234,
		"url":"http://s.handu.com/images/201708/thumb_img/1503432660825646787.jpg"
	},{
		"name":"韩都衣舍2016秋装韩版百搭",
		"price":4325.00,
		"xiao":34,
		"contents":43,
		"id":1245,
		"url":"http://s.handu.com/images/201703/thumb_img/1489781417259079571.jpg"
	},{
		"name":"韩都衣舍2016秋装韩版百搭",
		"price":543.00,
		"xiao":3123,
		"contents":56,
		"id":1246,
		"url":"http://s.handu.com/images/201709/thumb_img/1506715838430079469.jpg"
	},{
		"name":"韩都衣舍2016秋装韩版百搭",
		"price":79.00,
		"xiao":86,
		"contents":75,
		"id":1247,
		"url":"http://s.handu.com/images/201709/thumb_img/1506024659288448285.jpg"
	},{
		"name":"韩都衣舍2016秋装韩版百搭",
		"price":478.00,
		"xiao":34,
		"contents":765,
		"id":1248,
		"url":"http://s.handu.com/images/201703/thumb_img/1489695045135412556.jpg"
	},{
		"name":"韩都衣舍2016秋装韩版百搭",
		"price":565.00,
		"xiao":345,
		"contents":786,
		"id":1249,
		"url":"http://s.handu.com/images/201708/thumb_img/1502568628263654127.jpg"
	},{
		"name":"韩都衣舍2016秋装韩版百搭",
		"price":467.00,
		"xiao":472,
		"contents":83,
		"id":1250,
		"url":"http://s.handu.com/images/201709/thumb_img/1504383010349786942.jpg"
	},{
		"name":"韩都衣舍2016秋装韩版百搭",
		"price":34.00,
		"xiao":54,
		"contents":62,
		"id":1251,
		"url":"http://s.handu.com/images/201709/thumb_img/1504296632127681400.jpg"
	},{
		"name":"韩都衣舍2016秋装韩版百搭",
		"price":466.00,
		"xiao":573,
		"contents":452,
		"id":1252,
		"url":"http://s.handu.com/images/201704/thumb_img/1493323811451973072.jpg"
	},{
		"name":"韩都衣舍2016秋装韩版百搭",
		"price":342.00,
		"xiao":15,
		"contents":54,
		"id":1253,
		"url":"http://s.handu.com/images/201703/thumb_img/1488312649709027465.jpg"
	},{
		"name":"韩都衣舍2016秋装韩版百搭",
		"price":654.00,
		"xiao":74,
		"contents":51,
		"id":1254,
		"url":"http://s.handu.com/images/201708/thumb_img/1503432633419544649.jpg"
	},{
		"name":"韩都衣舍2016秋装韩版百搭",
		"price":634.00,
		"xiao":654,
		"contents":62,
		"id":1255,
		"url":"http://s.handu.com/images/201707/thumb_img/1501272663150993279.jpg"
	},{
		"name":"韩都衣舍2016秋装韩版百搭",
		"price":35.00,
		"xiao":25,
		"contents":753,
		"id":1256,
		"url":"http://s.handu.com/images/201605/thumb_img/1463343062523682099.jpg"
	},{
		"name":"韩都衣舍2016秋装韩版百搭",
		"price":35.00,
		"xiao":64,
		"contents":73,
		"id":1257,
		"url":"http://s.handu.com/images/201704/thumb_img/1490991015662929093.jpg"
	},{
		"name":"韩都衣舍2016秋装韩版百搭",
		"price":633.00,
		"xiao":26,
		"contents":64,
		"id":1258,
		"url":"http://s.handu.com/images/201608/thumb_img/1470773466136458946.jpg"
	},{
		"name":"韩都衣舍2016秋装韩版百搭",
		"price":25.00,
		"xiao":3643,
		"contents":75,
		"id":1259,
		"url":"http://s.handu.com/images/201608/thumb_img/1471551063625516912.jpg"
	},{
		"name":"韩都衣舍2016秋装韩版百搭",
		"price":57.00,
		"xiao":73,
		"contents":95,
		"id":1260,
		"url":"http://s.handu.com/images/201704/thumb_img/1493323818699400872.jpg"
	},{
		"name":"韩都衣舍2016秋装韩版百搭",
		"price":537.00,
		"xiao":64,
		"contents":86,
		"id":1261,
		"url":"http://s.handu.com/images/201709/thumb_img/1506715840076015143.jpg"
	},{
		"name":"韩都衣舍2016秋装韩版百搭",
		"price":753.00,
		"xiao":84,
		"contents":632,
		"id":1262,
		"url":"http://s.handu.com/images/201605/thumb_img/1463256640144256437.jpg"
	},{
		"name":"韩都衣舍2016秋装韩版百搭",
		"price":634.00,
		"xiao":786,
		"contents":46,
		"id":1263,
		"url":"http://s.handu.com/images/201707/thumb_img/1501272704936123358.jpg"
	},{
		"name":"韩都衣舍2016秋装韩版百搭",
		"price":754.00,
		"xiao":87,
		"contents":85,
		"id":1264,
		"url":"http://s.handu.com/images/201704/thumb_img/1491855095200850057.jpg"
	},{
		"name":"韩都衣舍2016秋装韩版百搭",
		"price":756.00,
		"xiao":81,
		"contents":70,
		"id":1265,
		"url":"http://s.handu.com/images/201709/thumb_img/1504728715928758501.jpg"
	},{
		"name":"韩都衣舍2016秋装韩版百搭",
		"price":805.00,
		"xiao":70,
		"contents":3,
		"id":1266,		
		"url":"http://s.handu.com/images/201609/thumb_img/1046131_thumb_G_1473843851049.jpg"
	},{
		"name":"韩都衣舍2016秋装韩版百搭",
		"price":675.00,
		"xiao":746,
		"contents":678,
		"id":1267,
		"url":"http://s.handu.com/images/201708/thumb_img/1502395837350264937.jpg"
	},{
		"name":"韩都衣舍2016秋装韩版百搭",
		"price":86.00,
		"xiao":743,
		"contents":295,
		"id":1268,
		"url":"http://s.handu.com/images/201709/thumb_img/1506715838430079469.jpg"
	},{
		"name":"韩都衣舍2016秋装韩版百搭",
		"price":754.00,
		"xiao":35,
		"contents":63,
		"id":1269,
		"url":"http://s.handu.com/images/201707/thumb_img/1499199060080994589.jpg"
	},{
		"name":"韩都衣舍2016秋装韩版百搭",
		"price":531.00,
		"xiao":62,
		"contents":26,
		"id":1270,
		"url":"http://s.handu.com/images/201707/thumb_img/1500862591671331961.jpg"
	},{
		"name":"韩都衣舍2016秋装韩版百搭",
		"price":531.00,
		"xiao":62,
		"contents":26,
		"id":1270,
		"url":"http://s.handu.com/images/201707/thumb_img/1500862591671331961.jpg"
	},{
		"name":"韩都衣舍2016秋装韩版百搭",
		"price":57.00,
		"xiao":73,
		"contents":95,
		"id":1260,
		"url":"http://s.handu.com/images/201704/thumb_img/1493323818699400872.jpg"
	},{
		"name":"韩都衣舍2016秋装韩版百搭",
		"price":537.00,
		"xiao":64,
		"contents":86,
		"id":1261,
		"url":"http://s.handu.com/images/201709/thumb_img/1506715840076015143.jpg"
	},{
		"name":"韩都衣舍2016秋装韩版百搭",
		"price":753.00,
		"xiao":84,
		"contents":632,
		"id":1262,
		"url":"http://s.handu.com/images/201605/thumb_img/1463256640144256437.jpg"
	},{
		"name":"韩都衣舍2016秋装韩版百搭",
		"price":634.00,
		"xiao":786,
		"contents":46,
		"id":1263,
		"url":"http://s.handu.com/images/201707/thumb_img/1501272704936123358.jpg"
	},{
		"name":"韩都衣舍2016秋装韩版百搭",
		"price":754.00,
		"xiao":87,
		"contents":85,
		"id":1264,
		"url":"http://s.handu.com/images/201704/thumb_img/1491855095200850057.jpg"
	},{
		"name":"韩都衣舍2016秋装韩版百搭",
		"price":756.00,
		"xiao":81,
		"contents":70,
		"id":1265,
		"url":"http://s.handu.com/images/201709/thumb_img/1504728715928758501.jpg"
	},{
		"name":"韩都衣舍2016秋装韩版百搭",
		"price":805.00,
		"xiao":70,
		"contents":3,
		"id":1266,		
		"url":"http://s.handu.com/images/201609/thumb_img/1046131_thumb_G_1473843851049.jpg"
	},{
		"name":"韩都衣舍2016秋装韩版百搭",
		"price":675.00,
		"xiao":746,
		"contents":678,
		"id":1267,
		"url":"http://s.handu.com/images/201708/thumb_img/1502395837350264937.jpg"
	},{
		"name":"韩都衣舍2016秋装韩版百搭",
		"price":86.00,
		"xiao":743,
		"contents":295,
		"id":1268,
		"url":"http://s.handu.com/images/201709/thumb_img/1506715838430079469.jpg"
	},{
		"name":"韩都衣舍2016秋装韩版百搭",
		"price":754.00,
		"xiao":35,
		"contents":63,
		"id":1269,
		"url":"http://s.handu.com/images/201707/thumb_img/1499199060080994589.jpg"
	},{
		"name":"韩都衣舍2016秋装韩版百搭",
		"price":531.00,
		"xiao":62,
		"contents":26,
		"id":1270,
		"url":"http://s.handu.com/images/201707/thumb_img/1500862591671331961.jpg"
	},{
		"name":"韩都衣舍2016秋装韩版百搭",
		"price":531.00,
		"xiao":62,
		"contents":26,
		"id":1270,
		"url":"http://s.handu.com/images/201707/thumb_img/1500862591671331961.jpg"
	},{
		"name":"韩都衣舍2016秋装韩版百搭",
		"price":805.00,
		"xiao":70,
		"contents":3,
		"id":1266,		
		"url":"http://s.handu.com/images/201609/thumb_img/1046131_thumb_G_1473843851049.jpg"
	},{
		"name":"韩都衣舍2016秋装韩版百搭",
		"price":675.00,
		"xiao":746,
		"contents":678,
		"id":1267,
		"url":"http://s.handu.com/images/201708/thumb_img/1502395837350264937.jpg"
	},{
		"name":"韩都衣舍2016秋装韩版百搭",
		"price":86.00,
		"xiao":743,
		"contents":295,
		"id":1268,
		"url":"http://s.handu.com/images/201709/thumb_img/1506715838430079469.jpg"
	},{
		"name":"韩都衣舍2016秋装韩版百搭",
		"price":754.00,
		"xiao":35,
		"contents":63,
		"id":1269,
		"url":"http://s.handu.com/images/201707/thumb_img/1499199060080994589.jpg"
	},{
		"name":"韩都衣舍2016秋装韩版百搭",
		"price":531.00,
		"xiao":62,
		"contents":26,
		"id":1270,
		"url":"http://s.handu.com/images/201707/thumb_img/1500862591671331961.jpg"
	},{
		"name":"韩都衣舍2016秋装韩版百搭",
		"price":531.00,
		"xiao":62,
		"contents":26,
		"id":1270,
		"url":"http://s.handu.com/images/201707/thumb_img/1500862591671331961.jpg"
	},{
		"name":"韩都衣舍2016秋装韩版百搭",
		"price":57.00,
		"xiao":73,
		"contents":95,
		"id":1260,
		"url":"http://s.handu.com/images/201704/thumb_img/1493323818699400872.jpg"
	},{
		"name":"韩都衣舍2016秋装韩版百搭",
		"price":537.00,
		"xiao":64,
		"contents":86,
		"id":1261,
		"url":"http://s.handu.com/images/201709/thumb_img/1506715840076015143.jpg"
	},{
		"name":"韩都衣舍2016秋装韩版百搭",
		"price":753.00,
		"xiao":84,
		"contents":632,
		"id":1262,
		"url":"http://s.handu.com/images/201605/thumb_img/1463256640144256437.jpg"
	},{
		"name":"韩都衣舍2016秋装韩版百搭",
		"price":634.00,
		"xiao":786,
		"contents":46,
		"id":1263,
		"url":"http://s.handu.com/images/201707/thumb_img/1501272704936123358.jpg"
	},{
		"name":"韩都衣舍2016秋装韩版百搭",
		"price":754.00,
		"xiao":87,
		"contents":85,
		"id":1264,
		"url":"http://s.handu.com/images/201704/thumb_img/1491855095200850057.jpg"
	},{
		"name":"韩都衣舍2016秋装韩版百搭",
		"price":756.00,
		"xiao":81,
		"contents":70,
		"id":1265,
		"url":"http://s.handu.com/images/201709/thumb_img/1504728715928758501.jpg"
	},{
		"name":"韩都衣舍2016秋装韩版百搭",
		"price":34.00,
		"xiao":54,
		"contents":62,
		"id":1251,
		"url":"http://s.handu.com/images/201709/thumb_img/1504296632127681400.jpg"
	},{
		"name":"韩都衣舍2016秋装韩版百搭",
		"price":466.00,
		"xiao":573,
		"contents":452,
		"id":1252,
		"url":"http://s.handu.com/images/201704/thumb_img/1493323811451973072.jpg"
	},{
		"name":"韩都衣舍2016秋装韩版百搭",
		"price":342.00,
		"xiao":15,
		"contents":54,
		"id":1253,
		"url":"http://s.handu.com/images/201703/thumb_img/1488312649709027465.jpg"
	},{
		"name":"韩都衣舍2016秋装韩版百搭",
		"price":654.00,
		"xiao":74,
		"contents":51,
		"id":1254,
		"url":"http://s.handu.com/images/201708/thumb_img/1503432633419544649.jpg"
	},{
		"name":"韩都衣舍2016秋装韩版百搭",
		"price":634.00,
		"xiao":654,
		"contents":62,
		"id":1255,
		"url":"http://s.handu.com/images/201707/thumb_img/1501272663150993279.jpg"
	},{
		"name":"韩都衣舍2016秋装韩版百搭",
		"price":35.00,
		"xiao":25,
		"contents":753,
		"id":1256,
		"url":"http://s.handu.com/images/201605/thumb_img/1463343062523682099.jpg"
	},{
		"name":"韩都衣舍2016秋装韩版百搭",
		"price":35.00,
		"xiao":64,
		"contents":73,
		"id":1257,
		"url":"http://s.handu.com/images/201704/thumb_img/1490991015662929093.jpg"
	},{
		"name":"韩都衣舍2016秋装韩版百搭",
		"price":633.00,
		"xiao":26,
		"contents":64,
		"id":1258,
		"url":"http://s.handu.com/images/201608/thumb_img/1470773466136458946.jpg"
	},{
		"name":"韩都衣舍2016秋装韩版百搭",
		"price":25.00,
		"xiao":3643,
		"contents":75,
		"id":1259,
		"url":"http://s.handu.com/images/201608/thumb_img/1471551063625516912.jpg"
	},{
		"name":"韩都衣舍2016秋装韩版百搭",
		"price":57.00,
		"xiao":73,
		"contents":95,
		"id":1260,
		"url":"http://s.handu.com/images/201704/thumb_img/1493323818699400872.jpg"
	},{
		"name":"韩都衣舍2016秋装韩版百搭",
		"price":537.00,
		"xiao":64,
		"contents":86,
		"id":1261,
		"url":"http://s.handu.com/images/201709/thumb_img/1506715840076015143.jpg"
	},{
		"name":"韩都衣舍2016秋装韩版百搭",
		"price":753.00,
		"xiao":84,
		"contents":632,
		"id":1262,
		"url":"http://s.handu.com/images/201605/thumb_img/1463256640144256437.jpg"
	},{
		"name":"韩都衣舍2016秋装韩版百搭",
		"price":634.00,
		"xiao":786,
		"contents":46,
		"id":1263,
		"url":"http://s.handu.com/images/201707/thumb_img/1501272704936123358.jpg"
	},{
		"name":"韩都衣舍2016秋装韩版百搭",
		"price":754.00,
		"xiao":87,
		"contents":85,
		"id":1264,
		"url":"http://s.handu.com/images/201704/thumb_img/1491855095200850057.jpg"
	},{
		"name":"韩都衣舍2016秋装韩版百搭",
		"price":756.00,
		"xiao":81,
		"contents":70,
		"id":1265,
		"url":"http://s.handu.com/images/201709/thumb_img/1504728715928758501.jpg"
	},{
		"name":"韩都衣舍2016秋装韩版百搭",
		"price":805.00,
		"xiao":70,
		"contents":3,
		"id":1266,		
		"url":"http://s.handu.com/images/201609/thumb_img/1046131_thumb_G_1473843851049.jpg"
	},{
		"name":"韩都衣舍2016秋装韩版百搭",
		"price":675.00,
		"xiao":746,
		"contents":678,
		"id":1267,
		"url":"http://s.handu.com/images/201708/thumb_img/1502395837350264937.jpg"
	},{
		"name":"韩都衣舍2016秋装韩版百搭",
		"price":466.00,
		"xiao":573,
		"contents":452,
		"id":1252,
		"url":"http://s.handu.com/images/201704/thumb_img/1493323811451973072.jpg"
	},{
		"name":"韩都衣舍2016秋装韩版百搭",
		"price":438.00,
		"xiao":323,
		"contents":223,
		"id":1232,
		"url":"http://s.handu.com/images/201709/thumb_img/1504987885123513412.jpg"
	},{
		"name":"韩都衣舍2016秋装韩版百搭",
		"price":48.00,
		"xiao":433,
		"contents":63,
		"id":1233,
		"url":"http://s.handu.com/images/201610/thumb_img/1477858289891674986.jpg"
	},{
		"name":"韩都衣舍2016秋装韩版百搭",
		"price":38.00,
		"xiao":32,
		"contents":73,
		"id":1234,
		"url":"http://s.handu.com/images/201607/thumb_img/1468527019657514084.jpg"
	},{
		"name":"韩都衣舍2016秋装韩版百搭",
		"price":4375.00,
		"xiao":33,
		"contents":27,
		"id":1235,
		"url":"http://s.handu.com/images/201605/thumb_img/1463256647982189429.jpg"
	},{
		"name":"韩都衣舍2016秋装韩版百搭",
		"price":98.00,
		"xiao":433,
		"contents":83,
		"id":1236,
		"url":"http://s.handu.com/images/201708/thumb_img/1503432636679267622.jpg"
	},{
		"name":"韩都衣舍2016秋装韩版百搭",
		"price":538.00,
		"xiao":3123,
		"contents":343,
		"id":1237,
		"url":"http://s.handu.com/images/201603/thumb_img/1459282501117262858.jpg"
	},{
		"name":"韩都衣舍2016秋装韩版百搭",
		"price":428.00,
		"xiao":63,
		"contents":133,
		"id":1238,
		"url":"http://s.handu.com/images/201703/thumb_img/1490472629482950873.jpg"
	},{
		"name":"韩都衣舍2016秋装韩版百搭",
		"price":138.00,
		"xiao":35,
		"contents":64,
		"id":1239,
		"url":"http://s.handu.com/images/201612/thumb_img/1480709466420407678.jpg"
	},{
		"name":"韩都衣舍2016秋装韩版百搭",
		"price":24.00,
		"xiao":335,
		"contents":223,
		"id":1240,
		"url":"http://s.handu.com/images/201703/thumb_img/1056203_thumb_G_1490252555160.jpg"
	},{
		"name":"韩都衣舍2016秋装韩版百搭",
		"price":3258.00,
		"xiao":3323,
		"contents":123,
		"id":1241,
		"url":"http://s.handu.com/images/201709/thumb_img/1504296651432586671.jpg"
	},{
		"name":"韩都衣舍2016秋装韩版百搭",
		"price":538.00,
		"xiao":3123,
		"contents":27,
		"id":1242,
		"url":"http://s.handu.com/images/201707/thumb_img/1501272612540619861.jpg"
	},{
		"name":"韩都衣舍2016秋装韩版百搭",
		"price":434.00,
		"xiao":312,
		"contents":245,
		"id":1243,
		"url":"http://s.handu.com/images/201705/thumb_img/1495138402759096558.jpg"
	},{
		"name":"韩都衣舍2016秋装韩版百搭",
		"price":432.00,
		"xiao":365,
		"contents":212,
		"id":1234,
		"url":"http://s.handu.com/images/201708/thumb_img/1503432660825646787.jpg"
	},{
		"name":"韩都衣舍2016秋装韩版百搭",
		"price":4325.00,
		"xiao":34,
		"contents":43,
		"id":1245,
		"url":"http://s.handu.com/images/201703/thumb_img/1489781417259079571.jpg"
	},{
		"name":"韩都衣舍2016秋装韩版百搭",
		"price":543.00,
		"xiao":3123,
		"contents":56,
		"id":1246,
		"url":"http://s.handu.com/images/201709/thumb_img/1506715838430079469.jpg"
	},{
		"name":"韩都衣舍2016秋装韩版百搭",
		"price":79.00,
		"xiao":86,
		"contents":75,
		"id":1247,
		"url":"http://s.handu.com/images/201709/thumb_img/1506024659288448285.jpg"
	},{
		"name":"韩都衣舍2016秋装韩版百搭",
		"price":478.00,
		"xiao":34,
		"contents":765,
		"id":1248,
		"url":"http://s.handu.com/images/201703/thumb_img/1489695045135412556.jpg"
	},{
		"name":"韩都衣舍2016秋装韩版百搭",
		"price":565.00,
		"xiao":345,
		"contents":786,
		"id":1249,
		"url":"http://s.handu.com/images/201708/thumb_img/1502568628263654127.jpg"
	},{
		"name":"韩都衣舍2016秋装韩版百搭",
		"price":467.00,
		"xiao":472,
		"contents":83,
		"id":1250,
		"url":"http://s.handu.com/images/201709/thumb_img/1504383010349786942.jpg"
	},{
		"name":"韩都衣舍2016秋装韩版百搭",
		"price":34.00,
		"xiao":54,
		"contents":62,
		"id":1251,
		"url":"http://s.handu.com/images/201709/thumb_img/1504296632127681400.jpg"
	},{
		"name":"韩都衣舍2016秋装韩版百搭",
		"price":466.00,
		"xiao":573,
		"contents":452,
		"id":1252,
		"url":"http://s.handu.com/images/201704/thumb_img/1493323811451973072.jpg"
	},{
		"name":"韩都衣舍2016秋装韩版百搭",
		"price":342.00,
		"xiao":15,
		"contents":54,
		"id":1253,
		"url":"http://s.handu.com/images/201703/thumb_img/1488312649709027465.jpg"
	},{
		"name":"韩都衣舍2016秋装韩版百搭",
		"price":654.00,
		"xiao":74,
		"contents":51,
		"id":1254,
		"url":"http://s.handu.com/images/201708/thumb_img/1503432633419544649.jpg"
	},{
		"name":"韩都衣舍2016秋装韩版百搭",
		"price":634.00,
		"xiao":654,
		"contents":62,
		"id":1255,
		"url":"http://s.handu.com/images/201707/thumb_img/1501272663150993279.jpg"
	},{
		"name":"韩都衣舍2016秋装韩版百搭",
		"price":35.00,
		"xiao":25,
		"contents":753,
		"id":1256,
		"url":"http://s.handu.com/images/201605/thumb_img/1463343062523682099.jpg"
	},{
		"name":"韩都衣舍2016秋装韩版百搭",
		"price":35.00,
		"xiao":64,
		"contents":73,
		"id":1257,
		"url":"http://s.handu.com/images/201704/thumb_img/1490991015662929093.jpg"
	},{
		"name":"韩都衣舍2016秋装韩版百搭",
		"price":633.00,
		"xiao":26,
		"contents":64,
		"id":1258,
		"url":"http://s.handu.com/images/201608/thumb_img/1470773466136458946.jpg"
	},{
		"name":"韩都衣舍2016秋装韩版百搭",
		"price":25.00,
		"xiao":3643,
		"contents":75,
		"id":1259,
		"url":"http://s.handu.com/images/201608/thumb_img/1471551063625516912.jpg"
	},{
		"name":"韩都衣舍2016秋装韩版百搭",
		"price":57.00,
		"xiao":73,
		"contents":95,
		"id":1260,
		"url":"http://s.handu.com/images/201704/thumb_img/1493323818699400872.jpg"
	},{
		"name":"韩都衣舍2016秋装韩版百搭",
		"price":537.00,
		"xiao":64,
		"contents":86,
		"id":1261,
		"url":"http://s.handu.com/images/201709/thumb_img/1506715840076015143.jpg"
	},{
		"name":"韩都衣舍2016秋装韩版百搭",
		"price":753.00,
		"xiao":84,
		"contents":632,
		"id":1262,
		"url":"http://s.handu.com/images/201605/thumb_img/1463256640144256437.jpg"
	},{
		"name":"韩都衣舍2016秋装韩版百搭",
		"price":634.00,
		"xiao":786,
		"contents":46,
		"id":1263,
		"url":"http://s.handu.com/images/201707/thumb_img/1501272704936123358.jpg"
	},{
		"name":"韩都衣舍2016秋装韩版百搭",
		"price":754.00,
		"xiao":87,
		"contents":85,
		"id":1264,
		"url":"http://s.handu.com/images/201704/thumb_img/1491855095200850057.jpg"
	},{
		"name":"韩都衣舍2016秋装韩版百搭",
		"price":756.00,
		"xiao":81,
		"contents":70,
		"id":1265,
		"url":"http://s.handu.com/images/201709/thumb_img/1504728715928758501.jpg"
	},{
		"name":"韩都衣舍2016秋装韩版百搭",
		"price":805.00,
		"xiao":70,
		"contents":3,
		"id":1266,		
		"url":"http://s.handu.com/images/201609/thumb_img/1046131_thumb_G_1473843851049.jpg"
	},{
		"name":"韩都衣舍2016秋装韩版百搭",
		"price":675.00,
		"xiao":746,
		"contents":678,
		"id":1267,
		"url":"http://s.handu.com/images/201708/thumb_img/1502395837350264937.jpg"
	},{
		"name":"韩都衣舍2016秋装韩版百搭",
		"price":86.00,
		"xiao":743,
		"contents":295,
		"id":1268,
		"url":"http://s.handu.com/images/201709/thumb_img/1506715838430079469.jpg"
	},{
		"name":"韩都衣舍2016秋装韩版百搭",
		"price":754.00,
		"xiao":35,
		"contents":63,
		"id":1269,
		"url":"http://s.handu.com/images/201707/thumb_img/1499199060080994589.jpg"
	},{
		"name":"韩都衣舍2016秋装韩版百搭",
		"price":531.00,
		"xiao":62,
		"contents":26,
		"id":1270,
		"url":"http://s.handu.com/images/201707/thumb_img/1500862591671331961.jpg"
	},{
		"name":"韩都衣舍2016秋装韩版百搭",
		"price":531.00,
		"xiao":62,
		"contents":26,
		"id":1270,
		"url":"http://s.handu.com/images/201707/thumb_img/1500862591671331961.jpg"
	},{
		"name":"韩都衣舍2016秋装韩版百搭",
		"price":57.00,
		"xiao":73,
		"contents":95,
		"id":1260,
		"url":"http://s.handu.com/images/201704/thumb_img/1493323818699400872.jpg"
	},{
		"name":"韩都衣舍2016秋装韩版百搭",
		"price":537.00,
		"xiao":64,
		"contents":86,
		"id":1261,
		"url":"http://s.handu.com/images/201709/thumb_img/1506715840076015143.jpg"
	},{
		"name":"韩都衣舍2016秋装韩版百搭",
		"price":753.00,
		"xiao":84,
		"contents":632,
		"id":1262,
		"url":"http://s.handu.com/images/201605/thumb_img/1463256640144256437.jpg"
	},{
		"name":"韩都衣舍2016秋装韩版百搭",
		"price":634.00,
		"xiao":786,
		"contents":46,
		"id":1263,
		"url":"http://s.handu.com/images/201707/thumb_img/1501272704936123358.jpg"
	},{
		"name":"韩都衣舍2016秋装韩版百搭",
		"price":754.00,
		"xiao":87,
		"contents":85,
		"id":1264,
		"url":"http://s.handu.com/images/201704/thumb_img/1491855095200850057.jpg"
	},{
		"name":"韩都衣舍2016秋装韩版百搭",
		"price":756.00,
		"xiao":81,
		"contents":70,
		"id":1265,
		"url":"http://s.handu.com/images/201709/thumb_img/1504728715928758501.jpg"
	},{
		"name":"韩都衣舍2016秋装韩版百搭",
		"price":805.00,
		"xiao":70,
		"contents":3,
		"id":1266,		
		"url":"http://s.handu.com/images/201609/thumb_img/1046131_thumb_G_1473843851049.jpg"
	},{
		"name":"韩都衣舍2016秋装韩版百搭",
		"price":675.00,
		"xiao":746,
		"contents":678,
		"id":1267,
		"url":"http://s.handu.com/images/201708/thumb_img/1502395837350264937.jpg"
	},{
		"name":"韩都衣舍2016秋装韩版百搭",
		"price":86.00,
		"xiao":743,
		"contents":295,
		"id":1268,
		"url":"http://s.handu.com/images/201709/thumb_img/1506715838430079469.jpg"
	},{
		"name":"韩都衣舍2016秋装韩版百搭",
		"price":754.00,
		"xiao":35,
		"contents":63,
		"id":1269,
		"url":"http://s.handu.com/images/201707/thumb_img/1499199060080994589.jpg"
	},{
		"name":"韩都衣舍2016秋装韩版百搭",
		"price":531.00,
		"xiao":62,
		"contents":26,
		"id":1270,
		"url":"http://s.handu.com/images/201707/thumb_img/1500862591671331961.jpg"
	},{
		"name":"韩都衣舍2016秋装韩版百搭",
		"price":531.00,
		"xiao":62,
		"contents":26,
		"id":1270,
		"url":"http://s.handu.com/images/201707/thumb_img/1500862591671331961.jpg"
	},{
		"name":"韩都衣舍2016秋装韩版百搭",
		"price":805.00,
		"xiao":70,
		"contents":3,
		"id":1266,		
		"url":"http://s.handu.com/images/201609/thumb_img/1046131_thumb_G_1473843851049.jpg"
	},{
		"name":"韩都衣舍2016秋装韩版百搭",
		"price":675.00,
		"xiao":746,
		"contents":678,
		"id":1267,
		"url":"http://s.handu.com/images/201708/thumb_img/1502395837350264937.jpg"
	},{
		"name":"韩都衣舍2016秋装韩版百搭",
		"price":86.00,
		"xiao":743,
		"contents":295,
		"id":1268,
		"url":"http://s.handu.com/images/201709/thumb_img/1506715838430079469.jpg"
	},{
		"name":"韩都衣舍2016秋装韩版百搭",
		"price":754.00,
		"xiao":35,
		"contents":63,
		"id":1269,
		"url":"http://s.handu.com/images/201707/thumb_img/1499199060080994589.jpg"
	},{
		"name":"韩都衣舍2016秋装韩版百搭",
		"price":531.00,
		"xiao":62,
		"contents":26,
		"id":1270,
		"url":"http://s.handu.com/images/201707/thumb_img/1500862591671331961.jpg"
	},{
		"name":"韩都衣舍2016秋装韩版百搭",
		"price":531.00,
		"xiao":62,
		"contents":26,
		"id":1270,
		"url":"http://s.handu.com/images/201707/thumb_img/1500862591671331961.jpg"
	},{
		"name":"韩都衣舍2016秋装韩版百搭",
		"price":57.00,
		"xiao":73,
		"contents":95,
		"id":1260,
		"url":"http://s.handu.com/images/201704/thumb_img/1493323818699400872.jpg"
	},{
		"name":"韩都衣舍2016秋装韩版百搭",
		"price":537.00,
		"xiao":64,
		"contents":86,
		"id":1261,
		"url":"http://s.handu.com/images/201709/thumb_img/1506715840076015143.jpg"
	},{
		"name":"韩都衣舍2016秋装韩版百搭",
		"price":753.00,
		"xiao":84,
		"contents":632,
		"id":1262,
		"url":"http://s.handu.com/images/201605/thumb_img/1463256640144256437.jpg"
	},{
		"name":"韩都衣舍2016秋装韩版百搭",
		"price":634.00,
		"xiao":786,
		"contents":46,
		"id":1263,
		"url":"http://s.handu.com/images/201707/thumb_img/1501272704936123358.jpg"
	},{
		"name":"韩都衣舍2016秋装韩版百搭",
		"price":754.00,
		"xiao":87,
		"contents":85,
		"id":1264,
		"url":"http://s.handu.com/images/201704/thumb_img/1491855095200850057.jpg"
	},{
		"name":"韩都衣舍2016秋装韩版百搭",
		"price":756.00,
		"xiao":81,
		"contents":70,
		"id":1265,
		"url":"http://s.handu.com/images/201709/thumb_img/1504728715928758501.jpg"
	},{
		"name":"韩都衣舍2016秋装韩版百搭",
		"price":34.00,
		"xiao":54,
		"contents":62,
		"id":1251,
		"url":"http://s.handu.com/images/201709/thumb_img/1504296632127681400.jpg"
	},{
		"name":"韩都衣舍2016秋装韩版百搭",
		"price":466.00,
		"xiao":573,
		"contents":452,
		"id":1252,
		"url":"http://s.handu.com/images/201704/thumb_img/1493323811451973072.jpg"
	},{
		"name":"韩都衣舍2016秋装韩版百搭",
		"price":342.00,
		"xiao":15,
		"contents":54,
		"id":1253,
		"url":"http://s.handu.com/images/201703/thumb_img/1488312649709027465.jpg"
	},{
		"name":"韩都衣舍2016秋装韩版百搭",
		"price":654.00,
		"xiao":74,
		"contents":51,
		"id":1254,
		"url":"http://s.handu.com/images/201708/thumb_img/1503432633419544649.jpg"
	},{
		"name":"韩都衣舍2016秋装韩版百搭",
		"price":634.00,
		"xiao":654,
		"contents":62,
		"id":1255,
		"url":"http://s.handu.com/images/201707/thumb_img/1501272663150993279.jpg"
	},{
		"name":"韩都衣舍2016秋装韩版百搭",
		"price":35.00,
		"xiao":25,
		"contents":753,
		"id":1256,
		"url":"http://s.handu.com/images/201605/thumb_img/1463343062523682099.jpg"
	},{
		"name":"韩都衣舍2016秋装韩版百搭",
		"price":35.00,
		"xiao":64,
		"contents":73,
		"id":1257,
		"url":"http://s.handu.com/images/201704/thumb_img/1490991015662929093.jpg"
	},{
		"name":"韩都衣舍2016秋装韩版百搭",
		"price":633.00,
		"xiao":26,
		"contents":64,
		"id":1258,
		"url":"http://s.handu.com/images/201608/thumb_img/1470773466136458946.jpg"
	},{
		"name":"韩都衣舍2016秋装韩版百搭",
		"price":25.00,
		"xiao":3643,
		"contents":75,
		"id":1259,
		"url":"http://s.handu.com/images/201608/thumb_img/1471551063625516912.jpg"
	},{
		"name":"韩都衣舍2016秋装韩版百搭",
		"price":57.00,
		"xiao":73,
		"contents":95,
		"id":1260,
		"url":"http://s.handu.com/images/201704/thumb_img/1493323818699400872.jpg"
	},{
		"name":"韩都衣舍2016秋装韩版百搭",
		"price":537.00,
		"xiao":64,
		"contents":86,
		"id":1261,
		"url":"http://s.handu.com/images/201709/thumb_img/1506715840076015143.jpg"
	},{
		"name":"韩都衣舍2016秋装韩版百搭",
		"price":753.00,
		"xiao":84,
		"contents":632,
		"id":1262,
		"url":"http://s.handu.com/images/201605/thumb_img/1463256640144256437.jpg"
	},{
		"name":"韩都衣舍2016秋装韩版百搭",
		"price":634.00,
		"xiao":786,
		"contents":46,
		"id":1263,
		"url":"http://s.handu.com/images/201707/thumb_img/1501272704936123358.jpg"
	},{
		"name":"韩都衣舍2016秋装韩版百搭",
		"price":754.00,
		"xiao":87,
		"contents":85,
		"id":1264,
		"url":"http://s.handu.com/images/201704/thumb_img/1491855095200850057.jpg"
	},{
		"name":"韩都衣舍2016秋装韩版百搭",
		"price":756.00,
		"xiao":81,
		"contents":70,
		"id":1265,
		"url":"http://s.handu.com/images/201709/thumb_img/1504728715928758501.jpg"
	},{
		"name":"韩都衣舍2016秋装韩版百搭",
		"price":805.00,
		"xiao":70,
		"contents":3,
		"id":1266,		
		"url":"http://s.handu.com/images/201609/thumb_img/1046131_thumb_G_1473843851049.jpg"
	},{
		"name":"韩都衣舍2016秋装韩版百搭",
		"price":675.00,
		"xiao":746,
		"contents":678,
		"id":1267,
		"url":"http://s.handu.com/images/201708/thumb_img/1502395837350264937.jpg"
	},{
		"name":"韩都衣舍2016秋装韩版百搭",
		"price":466.00,
		"xiao":573,
		"contents":452,
		"id":1252,
		"url":"http://s.handu.com/images/201704/thumb_img/1493323811451973072.jpg"
	}]
}